fionautil/__init__.py
fionautil/coords.py
fionautil/drivers.py
fionautil/feature.py
fionautil/geometry.py
fionautil/layer.py
fionautil/measure.py
fionautil/round.py
fionautil/scale.py
tests/__init__.py
tests/test_coords.py
tests/test_feature.py
tests/test_geometry.py
tests/test_layer.py
tests/test_measure.py
tests/test_round.py
tests/test_scale.py
tests/fixtures/testing.dbf
tests/fixtures/testing.geojson
tests/fixtures/testing.prj
tests/fixtures/testing.qpj
tests/fixtures/testing.shp
tests/fixtures/testing.shx
fionautil-0.7.0.dist-info/METADATA
fionautil-0.7.0.dist-info/WHEEL
fionautil-0.7.0.dist-info/top_level.txt
fionautil-0.7.0.dist-info/RECORD
