Metadata-Version: 2.1
Name: fionautil
Version: 0.7.0
Summary: helpful utilities for working with geodata with Fiona
Home-page: http://github.com/fitnr/fionautil/
Author: Neil Freeman
Author-email: contact@fakeisthenewreal.org
License: GNU General Public License v3 (GPLv3)
Keywords: GIS
Platform: UNKNOWN
Classifier: Development Status :: 4 - Beta
Classifier: Intended Audience :: Developers
Classifier: License :: OSI Approved :: GNU General Public License v3 (GPLv3)
Classifier: Programming Language :: Python :: 3.6
Classifier: Programming Language :: Python :: 3.7
Classifier: Programming Language :: Python :: 3.8
Classifier: Operating System :: OS Independent
Provides-Extra: azimuth
Provides-Extra: length
Provides-Extra: speed
Provides-Extra: shapify
Provides-Extra: dissolve
Provides-Extra: shape
